scrapy_warc/__init__.py
scrapy_warc/warcio.py
scrapy_warc/downloadmiddlewares/__init__.py
scrapy_warc/downloadmiddlewares/warcio.py
scrapy_warc-0.10.0.dist-info/LICENSE-APACHE
scrapy_warc-0.10.0.dist-info/LICENSE-MIT
scrapy_warc-0.10.0.dist-info/METADATA
scrapy_warc-0.10.0.dist-info/WHEEL
scrapy_warc-0.10.0.dist-info/top_level.txt
scrapy_warc-0.10.0.dist-info/RECORD
