Metadata-Version: 2.1
Name: scrapy-warc
Version: 0.10.0
Summary: UNKNOWN
Home-page: https://github.com/_/scrapy_warc
Author: Stefan Voshage
Author-email: s.voshage@gmx.de
Maintainer: Stefan Voshage
Maintainer-email: s.voshage@gmx.de
License: MIT/Apache-2.0
Platform: UNKNOWN
Classifier: Development Status :: 4 - Beta
Classifier: Intended Audience :: Developers
Classifier: License :: OSI Approved :: MIT License
Classifier: License :: OSI Approved :: Apache Software License
Classifier: Natural Language :: English
Classifier: Operating System :: OS Independent
Classifier: Programming Language :: Python :: 2.7
Classifier: Programming Language :: Python :: 3.5
Classifier: Programming Language :: Python :: 3.6
Classifier: Programming Language :: Python :: Implementation :: CPython
Classifier: Programming Language :: Python :: Implementation :: PyPy
